CHANGES.rst
COPYRIGHT.txt
LICENSE.txt
MANIFEST.in
README.rst
setup.py
src/zope/__init__.py
src/zope.outputchecker.egg-info/PKG-INFO
src/zope.outputchecker.egg-info/SOURCES.txt
src/zope.outputchecker.egg-info/dependency_links.txt
src/zope.outputchecker.egg-info/namespace_packages.txt
src/zope.outputchecker.egg-info/not-zip-safe
src/zope.outputchecker.egg-info/requires.txt
src/zope.outputchecker.egg-info/top_level.txt
src/zope/outputchecker/README.txt
src/zope/outputchecker/__init__.py
src/zope/outputchecker/checker.py
src/zope/outputchecker/tests.py